Workbook
Name Slicer_Month: #N/A
Name Slicer_Sales_Method: #N/A
Name Slicer_Product: #N/A
Name Slicer_Region: #N/A

Sheet Data
A1: ID Number | B1: Date | C1: Product | D1: Region | E1: Sales Method | F1: Price Per Unit | G1: Cost Per Unit | H1: Quantity | I1: Revenues | J1: Expenses | K1: Profit | L1: Expense/Revenue Ratio
A2: 10010 | B2: 44562 | C2: iphone | D2: EMEA | E2: In-store | F2: 1099 | G2: 289 | H2: 313.5 | I2: 344536.5 | J2: 90601.5 | K2: =I2-J2 -> 253935 | L2: =J2/I2 -> 0.26296633
A3: 10011 | B3: 44562 | C3: iphone | D3: North America | E3: Third Party | F3: 1099 | G3: 289 | H3: 300.7 | I3: 330469.3 | J3: 86902.3 | K3: =I3-J3 -> 243567 | L3: =J3/I3 -> 0.26296633
A4: 10012 | B4: 44562 | C4: macbook | D4: APAC | E4: Online Store | F4: 1299 | G4: 459 | H4: 482.2 | I4: 626377.8 | J4: 221329.8 | K4: =I4-J4 -> 405048 | L4: =J4/I4 -> 0.35334873
A5: 10013 | B5: 44562 | C5: ipad | D5: South America | E5: Referral | F5: 599 | G5: 299 | H5: 109 | I5: 65291 | J5: 32591 | K5: =I5-J5 -> 32700 | L5: =J5/I5 -> 0.49916528
A6: 10014 | B6: 44562 | C6: iwatch | D6: South America | E6: Online Store | F6: 449 | G6: 159 | H6: 450.9 | I6: 202454.1 | J6: 71693.1 | K6: =I6-J6 -> 130761 | L6: =J6/I6 -> 0.35412027
A7: 10015 | B7: 44562 | C7: airpod | D7: South America | E7: Online Store | F7: 199 | G7: 39 | H7: 270.9 | I7: 53909.1 | J7: 10565.1 | K7: =I7-J7 -> 43344 | L7: =J7/I7 -> 0.1959799
A8: 10016 | B8: 44565 | C8: airpod | D8: South America | E8: In-store | F8: 199 | G8: 39 | H8: 443.1 | I8: 88176.9 | J8: 17280.9 | K8: =I8-J8 -> 70896 | L8: =J8/I8 -> 0.1959799
A9: 10017 | B9: 44568 | C9: airpod | D9: EMEA | E9: Online Store | F9: 199 | G9: 39 | H9: 459.3 | I9: 91400.7 | J9: 17912.7 | K9: =I9-J9 -> 73488 | L9: =J9/I9 -> 0.1959799
A10: 10018 | B10: 44571 | C10: iphone | D10: North America | E10: Online Store | F10: 1099 | G10: 289 | H10: 222.5 | I10: 244527.5 | J10: 64302.5 | K10: =I10-J10 -> 180225 | L10: =J10/I10 -> 0.26296633
A11: 10019 | B11: 44574 | C11: macbook | D11: APAC | E11: In-store | F11: 1299 | G11: 459 | H11: 479.4 | I11: 622740.6 | J11: 220044.6 | K11: =I11-J11 -> 402696 | L11: =J11/I11 -> 0.35334873
A12: 10020 | B12: 44577 | C12: macbook | D12: APAC | E12: In-store | F12: 1299 | G12: 459 | H12: 301.2 | I12: 391258.8 | J12: 138250.8 | K12: =I12-J12 -> 253008 | L12: =J12/I12 -> 0.35334873
A13: 10021 | B13: 44580 | C13: airpod | D13: APAC | E13: In-store | F13: 199 | G13: 39 | H13: 315.1 | I13: 62704.9 | J13: 12288.9 | K13: =I13-J13 -> 50416 | L13: =J13/I13 -> 0.1959799
... A200: 10208 | B200: 44925 | C200: airpod | D200: EMEA | E200: Referral | F200: 199 | G200: 39 | H200: 361 | I200: 71839 | J200: 14079 | K200: =I200-J200 -> 57760 | L200: =J200/I200 -> 0.1959799

Sheet Working Sheet
A1: ID Number | B1: Date | C1: Month | D1: Product | E1: Region | F1: Sales Method | G1: Price Per Unit | H1: Cost Per Unit | I1: Quantity | J1: Revenues | K1: Expenses | L1: Profit | M1: Expense/Revenue Ratio
A2: 10010 | B2: 44562 | C2: =TEXT(B2,"MMM") -> Jan | D2: iphone | E2: EMEA | F2: In-store | G2: 1099 | H2: 289 | I2: 313.5 | J2: 344536.5 | K2: 90601.5 | L2: =J2-K2 -> 253935 | M2: =K2/J2 -> 0.26296633
A3: 10011 | B3: 44562 | C3: =TEXT(B3,"MMM") -> Jan | D3: iphone | E3: North America | F3: Third Party | G3: 1099 | H3: 289 | I3: 300.7 | J3: 330469.3 | K3: 86902.3 | L3: =J3-K3 -> 243567 | M3: =K3/J3 -> 0.26296633
A4: 10012 | B4: 44562 | C4: =TEXT(B4,"MMM") -> Jan | D4: macbook | E4: APAC | F4: Online Store | G4: 1299 | H4: 459 | I4: 482.2 | J4: 626377.8 | K4: 221329.8 | L4: =J4-K4 -> 405048 | M4: =K4/J4 -> 0.35334873
A5: 10013 | B5: 44562 | C5: =TEXT(B5,"MMM") -> Jan | D5: ipad | E5: South America | F5: Referral | G5: 599 | H5: 299 | I5: 109 | J5: 65291 | K5: 32591 | L5: =J5-K5 -> 32700 | M5: =K5/J5 -> 0.49916528
A6: 10014 | B6: 44562 | C6: =TEXT(B6,"MMM") -> Jan | D6: iwatch | E6: South America | F6: Online Store | G6: 449 | H6: 159 | I6: 450.9 | J6: 202454.1 | K6: 71693.1 | L6: =J6-K6 -> 130761 | M6: =K6/J6 -> 0.35412027
A7: 10015 | B7: 44562 | C7: =TEXT(B7,"MMM") -> Jan | D7: airpod | E7: South America | F7: Online Store | G7: 199 | H7: 39 | I7: 270.9 | J7: 53909.1 | K7: 10565.1 | L7: =J7-K7 -> 43344 | M7: =K7/J7 -> 0.1959799
A8: 10016 | B8: 44565 | C8: =TEXT(B8,"MMM") -> Jan | D8: airpod | E8: South America | F8: In-store | G8: 199 | H8: 39 | I8: 443.1 | J8: 88176.9 | K8: 17280.9 | L8: =J8-K8 -> 70896 | M8: =K8/J8 -> 0.1959799
A9: 10017 | B9: 44568 | C9: =TEXT(B9,"MMM") -> Jan | D9: airpod | E9: EMEA | F9: Online Store | G9: 199 | H9: 39 | I9: 459.3 | J9: 91400.7 | K9: 17912.7 | L9: =J9-K9 -> 73488 | M9: =K9/J9 -> 0.1959799
A10: 10018 | B10: 44571 | C10: =TEXT(B10,"MMM") -> Jan | D10: iphone | E10: North America | F10: Online Store | G10: 1099 | H10: 289 | I10: 222.5 | J10: 244527.5 | K10: 64302.5 | L10: =J10-K10 -> 180225 | M10: =K10/J10 -> 0.26296633
A11: 10019 | B11: 44574 | C11: =TEXT(B11,"MMM") -> Jan | D11: macbook | E11: APAC | F11: In-store | G11: 1299 | H11: 459 | I11: 479.4 | J11: 622740.6 | K11: 220044.6 | L11: =J11-K11 -> 402696 | M11: =K11/J11 -> 0.35334873
A12: 10020 | B12: 44577 | C12: =TEXT(B12,"MMM") -> Jan | D12: macbook | E12: APAC | F12: In-store | G12: 1299 | H12: 459 | I12: 301.2 | J12: 391258.8 | K12: 138250.8 | L12: =J12-K12 -> 253008 | M12: =K12/J12 -> 0.35334873
A13: 10021 | B13: 44580 | C13: =TEXT(B13,"MMM") -> Jan | D13: airpod | E13: APAC | F13: In-store | G13: 199 | H13: 39 | I13: 315.1 | J13: 62704.9 | K13: 12288.9 | L13: =J13-K13 -> 50416 | M13: =K13/J13 -> 0.1959799
... A200: 10208 | B200: 44925 | C200: =TEXT(B200,"MMM") -> Dec | D200: airpod | E200: EMEA | F200: Referral | G200: 199 | H200: 39 | I200: 361 | J200: 71839 | K200: 14079 | L200: =J200-K200 -> 57760 | M200: =K200/J200 -> 0.1959799

Sheet Pivot Table
A2: Sum of Quantity | B2: Sum of Revenues | C2: Sum of Expenses | D2: Sum of Profit | E2: Average of Expense/Revenue Ratio
A3: 54326.5 | B3: 36117848 | C3: 12061930 | D3: 24055919 | E3: 0.31042949
A6: Month | B6: Sum of Revenues | C6: Sum of Profit
A7: Dec | B7: 911242.5 | C7: 614840
A8: Apr | B8: 1793351.6 | C8: 1166932
A9: Jun | B9: 1981907.3 | C9: 1389456
A10: Feb | B10: 2111356 | C10: 1462150
A11: Mar | B11: 2783595 | C11: 1758368
A12: Sep | B12: 2860549.6 | C12: 1805362
A13: Jul | B13: 2986774.6 | C13: 2012362
A14: May | B14: 3401660.1 | C14: 2178235
A15: Jan | B15: 3419983.8 | C15: 2345618
A16: Nov | B16: 3617361.2 | C16: 2470778
A17: Oct | B17: 4558661.4 | C17: 3085812
A18: Aug | B18: 5691405.4 | C18: 3766006
A19: Grand Total | B19: 36117848 | C19: 24055919
A23: Product | B23: Sum of Profit
A24: iwatch | B24: 2231309
A25: ipad | B25: 3264320
A26: airpod | B26: 5430033
A27: iphone | B27: 6248921
A28: macbook | B28: 6881336
A29: Grand Total | B29: 24055919
A36: Region | B36: Sum of Profit
A37: EMEA | B37: 4261469
A38: South America | B38: 5315774
A39: North America | B39: 5317763
A40: APAC | B40: 9160913
A41: Grand Total | B41: 24055919
A48: Sales Method | B48: Sum of Revenues
A49: In-store | B49: 11252838
A50: Third Party | B50: 10533494
A51: Online Store | B51: 9716649.9
A52: Referral | B52: 4614866.7
A53: Grand Total | B53: 36117848

Sheet Dashboard
A1: Apple Data Set
C4: =GETPIVOTDATA("Sum of Quantity",'Pivot Table'!$A$2) -> 54326.5 | F4: =GETPIVOTDATA("Sum of Revenues",'Pivot Table'!$A$2) -> 36117848 | I4: =GETPIVOTDATA("Sum of Expenses",'Pivot Table'!$A$2) -> 12061930 | L4: =GETPIVOTDATA("Sum of Profit",'Pivot Table'!$A$2) -> 24055919 | O4: =GETPIVOTDATA("Average of Expense/Revenue Ratio",'Pivot Table'!$A$2) -> 0.31042949
